snr/__init__.py
snr/__main__.py
snr/snr.py
snr/constants/__init__.py
snr/constants/info.py
snr/constants/keybinds.py
snr/constants/messages.py
snr/parser/__init__.py
snr/parser/book_content.py
snr/parser/locale.json
snr/reader/__init__.py
snr/reader/config.py
snr/reader/config_reader.py
snr/reader/file_reader.py
snr/reader/state_reader.py
snr/screen/__init__.py
snr/screen/bookmark_describe_pages.py
snr/screen/bookmark_pages.py
snr/screen/content_pages.py
snr/screen/help_pages.py
snr/screen/pages.py
snr/screen/screen.py
snr/screen/toc_pages.py
snr/utilities/__init__.py
snr/utilities/bookmarks.py
snr/utilities/quickmarks.py
simple_novel_reader-0.9.212.dist-info/LICENSE
simple_novel_reader-0.9.212.dist-info/METADATA
simple_novel_reader-0.9.212.dist-info/WHEEL
simple_novel_reader-0.9.212.dist-info/entry_points.txt
simple_novel_reader-0.9.212.dist-info/top_level.txt
simple_novel_reader-0.9.212.dist-info/RECORD
