Metadata-Version: 2.1
Name: simple-novel-reader
Version: 0.9.212
Summary: An CLI light novel reader
Home-page: https://github.com/gzygmanski/simple-novel-reader
Author: Grzegorz Zygmański
Author-email: gzygmanski@hotmail.com
License: UNKNOWN
Keywords: cli curses ebook epub epub-reader,light-novel-reader light-novels
Platform: UNKNOWN
Classifier: Development Status :: 4 - Beta
Classifier: License :: OSI Approved :: MIT License
Classifier: Operating System :: Unix
Classifier: Environment :: Console :: Curses
Requires-Python: >=3.5, <4
Requires-Dist: beautifulsoup4
Requires-Dist: lxml
Requires-Dist: langcodes
Requires-Dist: PyHyphen
